python_autocomplete/__init__.py
python_autocomplete/bundle.py
python_autocomplete/create_dataset.py
python_autocomplete/distributed.py
python_autocomplete/serve.py
python_autocomplete/train.py
python_autocomplete/dataset/__init__.py
python_autocomplete/dataset/bpe.py
python_autocomplete/dataset/break_words.py
python_autocomplete/dataset/dataset.py
python_autocomplete/evaluate/__init__.py
python_autocomplete/evaluate/anomalies.py
python_autocomplete/evaluate/beam_search.py
python_autocomplete/evaluate/beam_search_lengthy.py
python_autocomplete/evaluate/eval_sample.py
python_autocomplete/evaluate/factory.py
python_autocomplete/evaluate/generate.py
python_autocomplete/models/__init__.py
python_autocomplete/models/highway.py
python_autocomplete/models/lstm.py
python_autocomplete/models/transformer.py
python_autocomplete/models/xl.py
labml_python_autocomplete-0.0.8.dist-info/LICENSE
labml_python_autocomplete-0.0.8.dist-info/METADATA
labml_python_autocomplete-0.0.8.dist-info/WHEEL
labml_python_autocomplete-0.0.8.dist-info/top_level.txt
labml_python_autocomplete-0.0.8.dist-info/RECORD
