Metadata-Version: 2.1
Name: labml-python-autocomplete
Version: 0.0.8
Summary: A simple model that learns to predict Python source code
Home-page: https://github.com/lab-ml/python_autocomplete
Author: Varuna Jayasiri
Author-email: vpjayasiri@gmail.com
License: UNKNOWN
Project-URL: Documentation, https://lab-ml.com/
Keywords: machine learning
Platform: UNKNOWN
Classifier: Programming Language :: Python :: 3
Classifier: License :: OSI Approved :: MIT License
Classifier: Intended Audience :: Developers
Classifier: Intended Audience :: Science/Research
Classifier: Topic :: Scientific/Engineering
Classifier: Topic :: Scientific/Engineering :: Mathematics
Classifier: Topic :: Scientific/Engineering :: Artificial Intelligence
Classifier: Topic :: Software Development
Classifier: Topic :: Software Development :: Libraries
Classifier: Topic :: Software Development :: Libraries :: Python Modules
Requires-Dist: labml (>=0.4.103)
Requires-Dist: labml-helpers (>=0.4.75)
Requires-Dist: labml-nn (>=0.4.88)
Requires-Dist: torch
Requires-Dist: einops
Requires-Dist: numpy
